LICENSE.txt
MANIFEST.in
README.rst
setup.py
src/envassert/__init__.py
src/envassert/command.py
src/envassert/cron.py
src/envassert/detect.py
src/envassert/file.py
src/envassert/filesystem.py
src/envassert/group.py
src/envassert/package.py
src/envassert/port.py
src/envassert/process.py
src/envassert/service.py
src/envassert/text.py
src/envassert/user.py
src/envassert.egg-info/PKG-INFO
src/envassert.egg-info/SOURCES.txt
src/envassert.egg-info/dependency_links.txt
src/envassert.egg-info/requires.txt
src/envassert.egg-info/top_level.txt