Metadata-Version: 1.1
Name: envassert
Version: 0.1.8
Summary: Test your servers environments by using fabric.
Home-page: http://bitbucket.org/r_rudi/envassert
Author: WAKAYAMA Shirou
Author-email: shirou.faw at gmail.com
License: MIT License
Download-URL: http://pypi.python.org/pypi/envassert
Keywords: test,server
Platform: UNKNOWN
Classifier: Development Status :: 3 - Alpha
Classifier: Intended Audience :: System Administrators
Classifier: License :: OSI Approved :: MIT License
Classifier: Programming Language :: Python
Classifier: Topic :: Software Development :: Testing
Classifier: Topic :: System :: Monitoring
Classifier: Topic :: System :: Systems Administration
